odoo/addons/base_fontawesome/README.rst
odoo/addons/base_fontawesome/__init__.py
odoo/addons/base_fontawesome/__manifest__.py
odoo/addons/base_fontawesome/__pycache__/__init__.cpython-37.pyc
odoo/addons/base_fontawesome/i18n/base_fontawesome.pot
odoo/addons/base_fontawesome/i18n/es_ES.po
odoo/addons/base_fontawesome/i18n/it.po
odoo/addons/base_fontawesome/i18n/zh_CN.po
odoo/addons/base_fontawesome/readme/CONTRIBUTORS.rst
odoo/addons/base_fontawesome/readme/DESCRIPTION.rst
odoo/addons/base_fontawesome/readme/USAGE.rst
odoo/addons/base_fontawesome/static/description/icon.png
odoo/addons/base_fontawesome/static/description/index.html
odoo/addons/base_fontawesome/static/lib/fontawesome-5.15.4/css/all.css
odoo/addons/base_fontawesome/static/lib/fontawesome-5.15.4/css/v4-shims.css
odoo/addons/base_fontawesome/static/lib/fontawesome-5.15.4/webfonts/fa-brands-400.eot
odoo/addons/base_fontawesome/static/lib/fontawesome-5.15.4/webfonts/fa-brands-400.svg
odoo/addons/base_fontawesome/static/lib/fontawesome-5.15.4/webfonts/fa-brands-400.ttf
odoo/addons/base_fontawesome/static/lib/fontawesome-5.15.4/webfonts/fa-brands-400.woff
odoo/addons/base_fontawesome/static/lib/fontawesome-5.15.4/webfonts/fa-brands-400.woff2
odoo/addons/base_fontawesome/static/lib/fontawesome-5.15.4/webfonts/fa-regular-400.eot
odoo/addons/base_fontawesome/static/lib/fontawesome-5.15.4/webfonts/fa-regular-400.svg
odoo/addons/base_fontawesome/static/lib/fontawesome-5.15.4/webfonts/fa-regular-400.ttf
odoo/addons/base_fontawesome/static/lib/fontawesome-5.15.4/webfonts/fa-regular-400.woff
odoo/addons/base_fontawesome/static/lib/fontawesome-5.15.4/webfonts/fa-regular-400.woff2
odoo/addons/base_fontawesome/static/lib/fontawesome-5.15.4/webfonts/fa-solid-900.eot
odoo/addons/base_fontawesome/static/lib/fontawesome-5.15.4/webfonts/fa-solid-900.svg
odoo/addons/base_fontawesome/static/lib/fontawesome-5.15.4/webfonts/fa-solid-900.ttf
odoo/addons/base_fontawesome/static/lib/fontawesome-5.15.4/webfonts/fa-solid-900.woff
odoo14_addon_base_fontawesome-14.0.5.15.5.dist-info/METADATA
odoo14_addon_base_fontawesome-14.0.5.15.5.dist-info/WHEEL
odoo14_addon_base_fontawesome-14.0.5.15.5.dist-info/top_level.txt
odoo14_addon_base_fontawesome-14.0.5.15.5.dist-info/RECORD
